{"@context":{"dcat":"https://www.w3.org/ns/dcat#","dcterms":"http://purl.org/dc/terms/","foaf":"http://xmlns.com/foaf/0.1/"},"@type":"dcterms:Collection","dcterms:hasPart":[{"foaf:page":"http://smartflanders.ilabt.imec.be/graph/undefined/catalog.json","@type":"dcat:Catalog"},{"foaf:page":"http://smartflanders.ilabt.imec.be/graph/9400/catalog.json","@type":"dcat:Catalog"},{"foaf:page":"http://smartflanders.ilabt.imec.be/graph/1800/catalog.json","@type":"dcat:Catalog"},{"foaf:page":"http://smartflanders.ilabt.imec.be/graph/9000/catalog.json","@type":"dcat:Catalog"},{"foaf:page":"http://smartflanders.ilabt.imec.be/graph/9300/catalog.json","@type":"dcat:Catalog"}]}